{
  "id": "stripe_receipt_tracking",
  "description": "Stripe payment receipt with Stripe-hosted receipt and click tracking links",
  "expected_verdicts": ["safe"],
  "expected_score_max": 28,
  "request": {
    "schema_version": "1.2",
    "from_email": "receipts@stripe.com",
    "display_name": "Stripe",
    "subject": "Your receipt from Example Store",
    "snippet": "Thank you for your payment. View your receipt. Payment received via Stripe.",
    "urls": [
      "https://dashboard.stripe.com/receipts/payment/abc",
      "https://click.stripe.com/track/abc123"
    ],
    "authentication": { "spf": "pass", "dkim": "pass", "dmarc": "pass" }
  }
}
